setup.py
py_protocol.egg-info/PKG-INFO
py_protocol.egg-info/SOURCES.txt
py_protocol.egg-info/dependency_links.txt
py_protocol.egg-info/top_level.txt
src/protocol/__init__.py