Metadata-Version: 2.1
Name: py-protocol
Version: 0.0.2
Summary: Support for network protocol senders
Author: Phuc Bao
